simple_chatwoot/__init__.py
simple_chatwoot/api.py
simple_chatwoot/utils.py
simple_chatwoot-0.0.2.dist-info/LICENSE
simple_chatwoot-0.0.2.dist-info/METADATA
simple_chatwoot-0.0.2.dist-info/WHEEL
simple_chatwoot-0.0.2.dist-info/top_level.txt
simple_chatwoot-0.0.2.dist-info/RECORD
