Metadata-Version: 2.1
Name: simple-chatwoot
Version: 0.0.2
Summary: A super simple package to connect to Chatwoot
Home-page: https://simple-chatwoot.readthedocs.io/
Author: Henrique Santana
Author-email: santana@cloudhumans.com
License: UNKNOWN
Project-URL: Bug Tracker, https://github.com/santana-ai/simple-chatwoot/issues
Platform: UNKNOWN
Classifier: Programming Language :: Python :: 3
Classifier: Programming Language :: Python :: 3.6
Classifier: Programming Language :: Python :: 3.7
Classifier: Programming Language :: Python :: 3.8
Classifier: Programming Language :: Python :: 3.9
Classifier: License :: OSI Approved :: MIT License
Classifier: Operating System :: OS Independent
Requires-Python: >=3.6
License-File: LICENSE
Requires-Dist: requests (>=2.27.1)
